dotdict.py
attr_dot_dict-0.1.0.dist-info/LICENSE
attr_dot_dict-0.1.0.dist-info/METADATA
attr_dot_dict-0.1.0.dist-info/WHEEL
attr_dot_dict-0.1.0.dist-info/top_level.txt
attr_dot_dict-0.1.0.dist-info/RECORD
