Metadata-Version: 2.1
Name: attr-dot-dict
Version: 0.1.0
Summary: A simple class that allows for the chaining of attributes.
Author-email: Nick Mireles <nick.mireles@dave.com>
License: GNU GENERAL PUBLIC LICENSE
Requires-Python: >=3.7
License-File: LICENSE
